{
	"id": "F6A07A4F-1E1F-41C0-ABAB-EEE4B3C9117F",
	"name": "Azure App Service Deployment",
	"category": "Deployment",
	"iconTaskId": "DCBEF2C9-E4F4-4929-82B2-EA7FC9166109",
	"description": "Deploy your Web, Mobile, and Function apps to Azure Web App.",
	"environment": {
		"name": "Production",
		"rank": 1,
		"deployPhases": [
			{
				"name": "Run on agent",
				"rank": 1,
				"phaseType": 1,
				"controlOptions": {},
				"deploymentInput": {
					"queueId": 1,
					"runOptions": {},
					"demands": []
				},
                "workflowTasks": [
                    {
                        "taskId": "94a74903-f93f-4075-884f-dc11f34058b4",
                        "version": "2.*",
                        "name": "Azure Deployment:Create Azure Resources",
                        "refName": "",
                        "enabled": true,
                        "alwaysRun": false,
                        "continueOnError": false,
                        "timeoutInMinutes": 0,
                        "definitionType": "task",
                        "overrideInputs": {},
                        "condition": "succeeded()",
                        "inputs": {
                            "ConnectedServiceName": "",
                            "action": "Create Or Update Resource Group",
                            "resourceGroupName": "",
                            "location": "",
                            "templateLocation": "Linked artifact",
                            "csmFileLink": "",
                            "csmParametersFileLink": "",
                            "csmFile": "",
                            "csmParametersFile": "",
                            "overrideParameters": "",
                            "deploymentMode": "Incremental",
                            "enableDeploymentPrerequisites": "None",
                            "deploymentGroupEndpoint": "",
                            "project": "",
                            "deploymentGroupName": "",
                            "copyAzureVMTags": "true",
                            "runAgentServiceAsUser": "false",
                            "userName": "",
                            "password": "",
                            "outputVariable": "",
                            "deploymentOutputs": ""
                        }
                    },
                    {
                        "taskId": "497d490f-eea7-4f2b-ab94-48d9c1acdcb1",
                        "version": "3.*",
                        "Name": "Deploy Azure App Service",
                        "inputs": {
                            "ConnectedServiceName": "",
                            "WebAppName": " ",
                            "WebAppKind": "app",
                            "DeployToSlotFlag": "false",
                            "ResourceGroupName": "",
                            "SlotName": "",
                            "DockerNamespace": "",
                            "DockerRepository": "",
                            "DockerImageTag": "$(Build.BuildId)",
                            "StartupCommand": "",
                            "VirtualApplication": "",
                            "Package": "$(System.DefaultWorkingDirectory)\\**\\*.zip",
                            "WebAppUri": "",
                            "ScriptType": "",
                            "InlineScript": "",
                            "ScriptPath": "",
                            "TakeAppOfflineFlag": "true",
                            "UseWebDeploy": "true",
                            "SetParametersFile": "",
                            "RemoveAdditionalFilesFlag": "false",
                            "ExcludeFilesFromAppDataFlag": "false",
                            "AdditionalArguments": "",
                            "RenameFilesFlag": "true",
                            "GenerateWebConfig": "false",
                            "WebConfigParameters": "",
                            "XmlTransformation": "false",
                            "XmlVariableSubstitution": "true",
                            "JSONFiles": "",
                            "AppSettings": "",
                            "ImageSource": "Registry",
                            "RuntimeStack": "",
                            "BuiltinLinuxPackage": "$(System.DefaultWorkingDirectory)/**/*.zip"
                        },
                        "Enabled": true,
                        "AlwaysRun": false,
                        "ContinueOnError": false
                    },
                    {
                        "taskId": "ce85a08b-a538-4d2b-8589-1d37a9ab970f",
                        "version": "1.*",
                        "name": "Execute Azure SQL",
                        "refName": "SqlAzureDacpacDeployment1",
                        "enabled": true,
                        "alwaysRun": false,
                        "continueOnError": false,
                        "timeoutInMinutes": 0,
                        "definitionType": "task",
                        "overrideInputs": {},
                        "condition": "succeeded()",
                        "inputs": {
                            "ConnectedServiceNameSelector": "ConnectedServiceNameARM",
                            "ConnectedServiceName": "",
                            "ConnectedServiceNameARM": "",
                            "ServerName": "",
                            "DatabaseName": " ",
                            "SqlUsername": "",
                            "SqlPassword": "",
                            "DeploymentAction": "Publish",
                            "TaskNameSelector": "",
                            "DacpacFile": "",
                            "BacpacFile": "",
                            "SqlFile": "",
                            "SqlInline": "",
                            "PublishProfile": "",
                            "AdditionalArguments": "/p:AllowIncompatiblePlatform=True",
                            "SqlAdditionalArguments": "",
                            "InlineAdditionalArguments": "",
                            "IpDetectionMethod": "AutoDetect",
                            "StartIpAddress": "",
                            "EndIpAddress": "",
                            "DeleteFirewallRule": "true"
                        }
                    }
                ]
			}
		],
		"deployStep": {
			"tasks": []
		},
		"preDeployApprovals": {
			"approvals": [
				{
					"isAutomated": true,
					"rank": 1
				}
			],
			"approvalOptions": null
		},
		"postDeployApprovals": {
			"approvals": [
				{
					"isAutomated": true,
					"rank": 1
				}
			],
			"approvalOptions": null
		},
		"runOptions": {}
	}
}
